Metadata-Version: 1.0
Name: love-distributions
Version: 0.2
Summary: makka
Home-page: UNKNOWN
Author: Curly
Author-email: curlymallu@gmail.com
License: UNKNOWN
Platform: UNKNOWN
